rtctools_simulation/__init__.py
rtctools_simulation/cli/reservoir.py
rtctools_simulation/empty_plot_table.csv
rtctools_simulation/interpolate.py
rtctools_simulation/lookup_table.py
rtctools_simulation/model.py
rtctools_simulation/model_config.py
rtctools_simulation/modelica/reservoir/lookup_table_equations.csv
rtctools_simulation/modelica/reservoir/reservoir.mo
rtctools_simulation/modelica/reservoir/reservoir_minq.mo
rtctools_simulation/optimization_problem.py
rtctools_simulation/reservoir/__init__.py
rtctools_simulation/reservoir/_input.py
rtctools_simulation/reservoir/_variables.py
rtctools_simulation/reservoir/minq.py
rtctools_simulation/reservoir/model.py
rtctools_simulation/reservoir/read_csv.py
rtctools_simulation/reservoir/rule_curve.py
rtctools_simulation/reservoir/setq_help_functions.py
rtctools_simulation/reservoir/template.py
rtctools_simulation/reservoir/template_data/input/plot_table.csv
rtctools_simulation/reservoir/template_data/input/rtcDataConfig.xml
rtctools_simulation/reservoir/template_data/input/rtcParameterConfig.xml
rtctools_simulation/reservoir/template_data/input/timeseries_import.xml
rtctools_simulation/reservoir/template_data/lookup_tables/h_qspill.csv
rtctools_simulation/reservoir/template_data/lookup_tables/lookup_tables.csv
rtctools_simulation/reservoir/template_data/lookup_tables/qout_v.csv
rtctools_simulation/reservoir/template_data/lookup_tables/v_area.csv
rtctools_simulation/reservoir/template_data/lookup_tables/v_h.csv
rtctools_simulation/reservoir/template_data/output/timeseries_export.xml
rtctools_simulation/reservoir/template_data/reservoir.txt
rtc_tools_simulation-0.2.0a7.dist-info/METADATA
rtc_tools_simulation-0.2.0a7.dist-info/WHEEL
rtc_tools_simulation-0.2.0a7.dist-info/entry_points.txt
rtc_tools_simulation-0.2.0a7.dist-info/RECORD
