Metadata-Version: 2.4
Name: rtc-tools-simulation
Version: 0.2.0a7
Summary: Extension for building models used for simulation in rtc-tools.
Author: Deltares
Requires-Python: >=3.9
Classifier: Programming Language :: Python :: 3
Classifier: Programming Language :: Python :: 3.9
Classifier: Programming Language :: Python :: 3.10
Classifier: Programming Language :: Python :: 3.11
Classifier: Programming Language :: Python :: 3.12
Classifier: Programming Language :: Python :: 3.13
Classifier: Programming Language :: Python :: 3.14
Requires-Dist: Jinja2
Requires-Dist: casadi (>=3.6.3,<=3.7,!=3.6.6)
Requires-Dist: numpy
Requires-Dist: pandas
Requires-Dist: pydantic
Requires-Dist: rtc-tools (>=2.7.0a4,<3.0.0)
Requires-Dist: rtc-tools-interface (>0.9)
